pyaudiotoolbox/__init__.py
pyaudiotoolbox/audio_converter.py
pyaudiotoolbox/audio_editor.py
pyaudiotoolbox/audio_extractor.py
pyaudiotoolbox/normalize_audio.py
tests/__init__.py
tests/test_audio_converter.py
tests/test_audio_extractor.py
pyaudiotoolbox-0.12.dist-info/LICENSE
pyaudiotoolbox-0.12.dist-info/METADATA
pyaudiotoolbox-0.12.dist-info/WHEEL
pyaudiotoolbox-0.12.dist-info/top_level.txt
pyaudiotoolbox-0.12.dist-info/RECORD
