Metadata-Version: 2.1
Name: pyaudiotoolbox
Version: 0.12
Summary: PyAudioToolBox is a python toolbox for basic audio editing and manipulations
Author: Abiodun Sulaiman
Author-email: hello@abiodun.dev
Project-URL: Source, https://github.com/abiodunsulaiman694/PyAudioToolBox
License-File: LICENSE
Requires-Dist: pydub
Requires-Dist: moviepy
